aenox/__init__.py
aenox/api.py
aenox/errors.py
aenox/models.py
aenox-0.1.6.dist-info/LICENSE
aenox-0.1.6.dist-info/METADATA
aenox-0.1.6.dist-info/WHEEL
aenox-0.1.6.dist-info/top_level.txt
aenox-0.1.6.dist-info/RECORD
