Metadata-Version: 2.2
Name: aenox
Version: 0.1.6
Summary: Official wrapper for the AenoX API
Author: aenoxic
License: MIT
Keywords: aenox,discord,bot,api
Classifier: Development Status :: 3 - Alpha
Classifier: License :: OSI Approved :: MIT License
Classifier: Intended Audience :: Developers
Classifier: Operating System :: OS Independent
Classifier: Programming Language :: Python :: 3.10
Classifier: Programming Language :: Python :: 3.11
Classifier: Programming Language :: Python :: 3.12
Requires-Python: >=3.10
License-File: LICENSE
Requires-Dist: python-dotenv
Requires-Dist: pymongo
Requires-Dist: requests
Requires-Dist: httpx
Requires-Dist: build
Requires-Dist: twine
